main.py
xeto-0.1.2.dist-info/licenses/LICENSE
xeto-0.1.2.dist-info/METADATA
xeto-0.1.2.dist-info/WHEEL
xeto-0.1.2.dist-info/top_level.txt
xeto-0.1.2.dist-info/RECORD
