Metadata-Version: 2.4
Name: xeto
Version: 0.1.2
Summary: Xeto data spec libraries
License-Expression: AFL-3.0
Requires-Python: >=3.14
License-File: LICENSE
Dynamic: license-file
